oauth2_sso/__init__.py
oauth2_sso/apps.py
oauth2_sso/backends.py
oauth2_sso/urls.py
oauth2_sso/views.py
oauth2_sso-0.3.1.dist-info/DESCRIPTION.rst
oauth2_sso-0.3.1.dist-info/METADATA
oauth2_sso-0.3.1.dist-info/RECORD
oauth2_sso-0.3.1.dist-info/WHEEL
oauth2_sso-0.3.1.dist-info/metadata.json
oauth2_sso-0.3.1.dist-info/top_level.txt
