Metadata-Version: 2.0
Name: oauth2-sso
Version: 0.3.1
Summary: Django OAuth 2 Authentication Made Easy
Home-page: https://github.com/saibot94/django-oauth2-sso
Author: Cristian Schuszter
Author-email: cristian.schuszter@cern.ch
License: MIT
Download-URL: https://github.com/saibot94/django-oauth2-sso/archive/0.1.tar.gz
Keywords: Django,user,management,sign-up,user sync,authentication,authorization,OAuth,SSO
Platform: UNKNOWN
Classifier: Development Status :: 4 - Beta
Classifier: Intended Audience :: Developers
Classifier: Topic :: Software Development :: Libraries :: Python Modules
Classifier: License :: OSI Approved :: MIT License
Classifier: Framework :: Django :: 1.6
Classifier: Framework :: Django :: 1.7
Classifier: Framework :: Django :: 1.8
Classifier: Framework :: Django :: 1.9
Classifier: Framework :: Django :: 1.10
Classifier: Programming Language :: Python :: 2
Classifier: Programming Language :: Python :: 2.7
Classifier: Programming Language :: Python :: 3
Classifier: Programming Language :: Python :: 3.4
Classifier: Programming Language :: Python :: 3.5
Classifier: Programming Language :: Python :: 3.6
Requires-Dist: Django (>=1.6)
Requires-Dist: requests (>=2.0.0)
